<?xml version="1.0" encoding="UTF-8"?>
<List>
<Item FileName="01" Caption="Флаги УСС"/>
<Item FileName="02" Caption="Стрелец легиона УСС"/>
<Item FileName="04" Caption="Украинские сечевые стрельцы"/>
<Item FileName="06" Caption="Михаил Грушевский"/>
<Item FileName="07" Caption="В редакции украинской газеты &quot;Родное слово&quot;. Австро-Венгрия, 1918 г."/>
<Item FileName="08" Caption="Симон Петлюра"/>
<Item FileName="09" Caption="Сечевые стрельцы слушают кобзаря"/>
<Item FileName="10" Caption="Атаман УСС, герой Купола Семен Горук"/>
<Item FileName="11" Caption="Гора Маковка в Карпатах"/>
<Item FileName="12" Caption="Командант УСС Антон Варивода"/>
<Item FileName="13" Caption="Группа сечевиков"/>
<Item FileName="14" Caption="Старшины сечевиков"/>
<Item FileName="15" Caption="Украинская Боевая управа"/>
<Item FileName="16" Caption="Старшины стрелкового корпуса"/>
<Item FileName="17" Caption="Стрелковые старшины"/>
<Item FileName="18" Caption="Автокоманды корпуса стрелков"/>
<Item FileName="19" Caption="Группа сечевых стрельцов"/>
</List>
