<?xml version="1.0" encoding="UTF-8"?>
<List>
<Item FileName="1" Caption="Лазарь Баранович. Гравюра Левицкого"/>
<Item FileName="2" Caption="Гравюра И. Мирского к книге С. Яворского, с изображением гетмана Мазепы с гербом. 1689"/>
<Item FileName="3" Caption="Феофан Прокопович"/>
<Item FileName="4" Caption="Стефан Яворский"/>
<Item FileName="5" Caption="Гравюра И. Мирского с изображением студентов Киево-Могилянской академии и ее главного корпуса"/>
<Item FileName="6" Caption="Страница рукописного сборника &quot;млеко&quot; Ивана Величковского с фигурным стихах"/>
<Item FileName="7" Caption="Киево-Братский монастырь со зданиями Киево-Могилянской академии"/>
<Item FileName="8" Caption="Титульный лист книги И. Галятовского &quot;Ключ разумения&quot;"/>
<Item FileName="9" Caption="&quot;Музыкальная грамматика&quot; М. Дилецкого. 1723"/>
<Item FileName="10" Caption="Титульный лист летописи Самуила Величко"/>
<Item FileName="11" Caption="Дом полковой канцелярии в Чернигове. Конец XVII в."/>
<Item FileName="12" Caption="Церковь Екатерины в Чернигове"/>
<Item FileName="13" Caption="Здание Черниговского коллегиума"/>
<Item FileName="14" Caption="Георгиевский собор Выдубицкого монастыря"/>
<Item FileName="15" Caption="Портрет cтародубського полковника Миклашевского - основателя Георгиевского собора в Киеве"/>
<Item FileName="16" Caption="Портрет выдающегося украинского государственного и военного деятеля второй половины XVIII в. Григория Гамалеи"/>
<Item FileName="17" Caption="Икона Вознесения. Работа И. Кондзелевича"/>
<Item FileName="18" Caption="Архангел Михаил 1698 - 1705 рр. Работа И. Рутковича"/>
<Item FileName="19" Caption="Казак Мамай"/>
<Item FileName="20" Caption="Икона Распятие с портретом Лубенского полковника Леонтия Свечи. XVII в."/>
<Item FileName="21" Caption="Троицкий казацкий собор в Новомосковске. XVIII в."/>
<Item FileName="22" Caption="Музыки. Народный рисунок XVIII в."/>
</List>
