<?xml version="1.0" encoding="UTF-8"?>
<List Title="Друга світова війна">
<Item FileName="1" Caption="Й.Сталін, Й.Ріббентроп (стоять другий та третій праворуч) і В.Молотов (сидить) під час підписання Договору про ненапад між Німеччиною та Радянським Союзом. Москва, 1939 р."/>
<Item FileName="2" Caption="Адольф Гітлер та Фрідріх Паулюс біля карти військових дій. 1940 р."/>
<Item FileName="3" Caption="А.Гітлер і В.Кейтель оглядають підірваний бронепоїзд. Польща, 1939 р."/>
<Item FileName="4" Caption="Жителі Варшави на будівництві барикад. 1939 р."/>
<Item FileName="5" Caption="Хлопчик на звалищі будинку. Варшава, 1940 р."/>
<Item FileName="6" Caption="Генерал-фельдмаршал Вільгельм Кейтель – начальник штабу верховного командування Німеччини"/>
<Item FileName="7" Caption="Вступ німецьких танків до Лівії. 1941 р."/>
<Item FileName="8" Caption="Гітлерівські мотоциклісти в лісах Ровенщини. 1941 р."/>
<Item FileName="9" Caption="Шарль де Голь. 40-і роки ХХ ст."/>
<Item FileName="10" Caption="Гітлерівці переходять річку на західному кордоні СРСР. 1941 р."/>
<Item FileName="11" Caption="Винищувачі, одержані зі США за програмою ленд-лізу. 1941 р."/>
<Item FileName="12" Caption="Німецький лінкор «Дойтчланд» (пізніше – «Лютцлов»). 1939 р."/>
<Item FileName="13" Caption="Німецькі мотоциклісти на вулицях Копенгагена. 1940 р."/>
<Item FileName="14" Caption="Німецькі солдати біля палаючого будинку фермера у Франції. 1940 р."/>
<Item FileName="15" Caption="Беніто Муссоліні оголошує війну Англії та Франції. 1940 р."/>
<Item FileName="16" Caption="Адмірал Ямамото очолював напад японців на Перл-Гарбор 7 грудня 1941 р."/>
<Item FileName="17" Caption="Фельдмаршал Роммель під час військових дій в Північній Африці. 1941 р."/>
<Item FileName="18" Caption="Японці беруть у полон  британських солдат. Сінгапур, 1942 р."/>
<Item FileName="19" Caption="Радянські танкісти перед наступом на м.Харків. 1942 р."/>
<Item FileName="20" Caption="Десантування моряків Чорноморського флоту на захоплену ворогом територію. 1942 р."/>
<Item FileName="22" Caption="С.Ковпак і С.Руднєв серед партизанів у Брянському лісі. 1942 р."/>
<Item FileName="23" Caption="Виробництво снарядів на одному з харківських заводів, евакуйованому на Урал. 1942 р."/>
<Item FileName="24" Caption="Вінстон Черчилль, прем’єр-міністр Великої Британії. 1943 р."/>
<Item FileName="25" Caption="Командувач військами союзників в південно-східній частині Тихого океану генерал Макартур. 1942 р."/>
<Item FileName="26" Caption="Англійці доставляють полонених у Дьєпі (Франція) німців до Англії. 1942 р."/>
<Item FileName="27" Caption="Радянський протитанковий підрозділ на шляху до Сталінграда. 1942 р."/>
<Item FileName="28" Caption="Учасники французького Опору з американським армійським офіцером. 1942 р."/>
<Item FileName="29" Caption="В.Черчилль і Ф.Рузвельт у Касабланці зі своїми радниками: генералом Маршаллом (сидить крайній праворуч) і лордом Маунтбеттеном (позаду Рузвельта). 1943 р."/>
<Item FileName="31" Caption="Рузвельт, Черчилль і Сталін святкують день народження прем‘єр-міністра Великої Британії. Тегеран, 1943 р."/>
<Item FileName="32" Caption="Радянський генерал Микола Ватутін під Курськом. 1943 р."/>
<Item FileName="33" Caption="Радянські солдати перед боєм під Курськом. 1943 р."/>
<Item FileName="34" Caption="Йосип Броз Тіто (праворуч) – югославський комуністичний лідер, організатор партизанського руху. 1943 р."/>
<Item FileName="35" Caption="Друга Вільна Французька бронетанкова дивізія проходить через Тріумфальну Арку після визволенння Парижа. 1944 р."/>
<Item FileName="36" Caption="Генерал Макартур на березі затоки Лейте (Філіппіни). 1944 р."/>
<Item FileName="37" Caption="Польський учасник опору в руках німецьких солдатів. Варшавське повстання 1944 р."/>
<Item FileName="38" Caption="Війська союзників переправляються через Рейн. 1945 р."/>
<Item FileName="39" Caption="Зустріч на  Ельбі  радянських, американських та англійських військових. Німеччина, 1945 р."/>
<Item FileName="40" Caption="Керівники держав антигітлерівської коаліції на Ялтинській конференції. 1945 р."/>
<Item FileName="41" Caption="В.Кейтель підписує Акт про беззастережну капітуляцію. Карлхорст (Німеччина), травень 1945 р."/>
<Item FileName="42" Caption="Зруйнований під час бомбардування будинок у Празі. 1945 р."/>
<Item FileName="43" Caption="Печі крематорію на території гітлерівського концтабору Освенцим. Польща, 1945 р."/>
<Item FileName="44" Caption="Дуайт Ейзенхауер, генерал-майор армії США в період Другої світової війни, згодом – президент США"/>
<Item FileName="45" Caption="Підписання Акта про капітуляцію Японії. 1945 р."/>
<Item FileName="46" Caption="Георгій Жуков – Маршал Радянського Союзу, видатний воєначальник часів Другої світової війни"/>
<Item FileName="47" Caption="Йосип Сталін – комуністичний лідер СРСР"/>
<Item FileName="48" Caption="Адольф Гітлер – вождь німецького націонал-соціалізму (з 1921 р.), керівник німецької фашистської держави (з 1933 р.)"/>
<Item FileName="49" Caption="Гітлер за кілька днів до самогубства. 1945 р."/>
<Item FileName="50" Caption="Позиції американських морських піхотинців на острові Іводзима. 1945 р."/>
<Item FileName="51" Caption="Американський морський піхотинець кидається на японске кулеметне гніздо на Окінаві. 1945 р."/>
<Item FileName="52" Caption="Жителі Мілана вітають американські війська. 1945 р."/>
<Item FileName="53" Caption="Останнє інтерв’ю Муссоліні. 1945 р."/>
<Item FileName="54" Caption="Святкування Дня Перемоги в Лондоні. 1945 р."/>
<Item FileName="55" Caption="Черчилль, Трумен і Сталін на Потсдамській конференції. 1945 р."/>
<Item FileName="56" Caption="Радянські моряки в Порт-Артурі. Манчжурія, 1945 р."/>
<Item FileName="57" Caption="Англійські солдати заходять в Рангун (Бірма). 1945 р."/>
<Item FileName="58" Caption="Прапор перемоги над рейхстагом. 1945 р."/>
<Item FileName="59" Caption="Нагасакі після вибуху американської атомної бомби. 1945 р."/>
</List>
