<?xml version="1.0" encoding="UTF-8"?>
<List>
<Item FileName="1" Caption="Гетьман Іван Скоропадський"/>
<Item FileName="2" Caption="Наказний гетьман Павло Полуботок"/>
<Item FileName="3" Caption="Гетьман Данило Апостол"/>
<Item FileName="4" Caption="Гетьман Кирило Розумовський"/>
<Item FileName="5" Caption="Спасо-Преображенська церква у Великих Сорочинцях на Полтавщині, збудована коштом Данила Апостола. 1732 р."/>
<Item FileName="6" Caption="Російська імператриця Єлизавета Петрівна"/>
<Item FileName="7" Caption="Російська імператриця Катерина ІІ"/>
<Item FileName="8" Caption="Указ Катерини ІІ про ліквідацію в Україні гетьманства 1764 р."/>
</List>
