<?xml version="1.0" encoding="UTF-8"?>
<List>
<Item FileName="43" Caption="Імператор Микола I"/>
<Item FileName="44" Caption="Севастопольська бухта"/>
<Item FileName="45" Caption="Кораблі біля Севастополя"/>
<Item FileName="46" Caption="Російський Чорноморський флот"/>
<Item FileName="47" Caption="Синопська битва. Кримська війна"/>
<Item FileName="48" Caption="Битва на Альмі. Кримська війна"/>
<Item FileName="49" Caption="Битва під Балаклавою. Кримська війна"/>
<Item FileName="50" Caption="Герой Кримської війни, адмірал Корнілов"/>
<Item FileName="51" Caption="Герой Кримської війни, адмірал Істомін"/>
<Item FileName="52" Caption="Герой Кримської війни, адмірал Нахімов"/>
<Item FileName="54" Caption="Імператор Олександр ІІ"/>
</List>
