<?xml version="1.0" encoding="UTF-8"?>
<List>
<Item FileName="05" Caption="Cathedral of the Nativity of the Virgin, 1752-1763 years, Kozelets"/>
<Item FileName="Cherni84" Caption="Transfiguration Cathedral, XI c., Chernigov"/>
<Item FileName="07" Caption="Friday Church, XII-XIII centuries. Chernigov"/>
<Item FileName="02" Caption="Chernihiv synthetic fiber"/>
<Item FileName="06" Caption="Palace manor Galaganov with. Sokirintsy, Srebnyansky borough"/>
<Item FileName="01" Caption="House regimental office, Chernigov"/>
<Item FileName="Crg_5" Caption="Cathedral of the Assumption, 1671, Novgorod-Seversky"/>
<Item FileName="Chernig_sl_4" Caption="Catherine Church, 1715, Chernigov"/>
<Item FileName="08" Caption="Dendro &quot;Trostianets&quot; with. Trostianets, Ichnyansky borough"/>
<Item FileName="03" Caption="Historical and Cultural Reserve &quot;Kachanivka&quot; with. Kachanivka, Ichnyansky borough"/>
<Item FileName="09" Caption="Church in a. Oral Kozeletskiy borough"/>
<Item FileName="04" Caption="K. Razumovsky Palace, town. Baturin, Bakhmach borough"/>
</List>
