<?xml version="1.0" encoding="UTF-8"?>
<List Title="EARTH - our common home">
<Item FileName="1" Caption="Sailing time of Christopher Columbus"/>
<Item FileName="2" Caption="Christopher Columbus"/>
<Item FileName="3" Caption="In Hawaii"/>
<Item FileName="4" Caption="At one of the markets Syanґana. China"/>
<Item FileName="5" Caption="Stay in China"/>
<Item FileName="6" Caption="During the traditional celebration. Ghana"/>
<Item FileName="7" Caption="Jap in national costumes"/>
<Item FileName="8" Caption="Boys with cattle. Madagascar"/>
<Item FileName="9" Caption="Japanese schoolgirl"/>
<Item FileName="10" Caption="Orthodox Church in Greece"/>
<Item FileName="11" Caption="Statue of Christ in Portugal"/>
<Item FileName="11_1" Caption="Basilica of Sts. Peter in the Vatican"/>
<Item FileName="12" Caption="Golden Buddha. China"/>
<Item FileName="13" Caption="The largest share of emissions falls on the industrialized nations"/>
<Item FileName="14" Caption="Founded in 1788, Sydney was the first European settlement in Australia"/>
</List>
