<?xml version="1.0" encoding="UTF-8"?>
<testing name="Соціальний устрій та господарське життя в Україні в другій половині XIV - першій половині XVI ст.">
  <question level="1" simple="True" text="Коли відбувся остаточний поділ Київської митрополії на Київську та Московську?">
    <answer text="У 1401 р." flag="0"/>
    <answer text="У 1458 р." flag="1"/>
  </question>
  <question level="1" simple="True" text="Яка верства посідала верхівку суспільної піраміди в XV - першій половині XVI ст.? ">
    <answer text="Шляхта" flag="1"/>
    <answer text="Селяни" flag="0"/>
    <answer text="Духівництво" flag="0"/>
  </question>
  <question level="1" simple="True" text="Яка верства тодішнього суспільства була найчисельнішою?">
    <answer text="Князі" flag="0"/>
    <answer text="Селяни" flag="1"/>
    <answer text="Духівництво" flag="0"/>
  </question>
  <question level="1" simple="True" text="Як називали категорію селян, основна повинність яких полягала у сплаті данини натурою або грішми за користування орними землями та угіддями">
    <answer text="Тяглові" flag="0"/>
    <answer text="Данники" flag="1"/>
  </question>
  <question level="1" simple="True" text="Що визначало становище селян, які працювали у фільварковому господарстві?">
    <answer text="Селяни сплачували натуральний чи грошовий податок" flag="0"/>
    <answer text="Селяни працювали в панському маєткові зі своїм «тяглом», їхні права щодо переходу обмежувалися" flag="1"/>
  </question>
  <question level="1" simple="True" text="Представник якої української князівської родини в першій чверті XVI ст. перебував на найвищих державних посадах, був четвертою за заможністю людиною в державі?">
    <answer text="Семен Олелькович" flag="0"/>
    <answer text="Костянтин Іванович Острозький" flag="1"/>
  </question>
  <question level="1" simple="True" text="Яка подія спричинила прилучення православних литовців та литовців-язичників до католицизму?">
    <answer text="Кревська унія" flag="1"/>
    <answer text="Утворення Руського воєводства Польщі" flag="0"/>
  </question>
  <question level="1" simple="True" text="Яка подія засвідчила поділ суспільства за релігійною ознакою та відкривала шлях для утисків православних?">
    <answer text="Ґрюнвальдська битва 1410 р., де було завдано нищівного удару лицарям-тевтонам" flag="0"/>
    <answer text="Городельська унія 1413 р., згідно з якою брати участь в управлінні державою та займати урядові посади отримували право виключно католики" flag="1"/>
  </question>
  <question level="1" simple="True" text="Які з міст, що входили до складу Великого князівства Литовського на початку 16 ст., були найбільшими?">
    <answer text="Київ, Брацлав, Кременець, Луцьк, Володимир" flag="1"/>
    <answer text="Белз, Холм, Дрогобич, Самбір, Рогатин" flag="0"/>
  </question>
  <question level="1" simple="True" text="Які з міст, що входили до складу Польщі на початку XVI ст., були найбільшими?">
    <answer text="Острог, Житомир, Черкаси" flag="0"/>
    <answer text="Львів, Кам'янець, Перемишль" flag="1"/>
  </question>
  <question level="1" simple="True" text="Що таке маґдебурзьке право?">
    <answer text="Право, за яким міста звільнялися від управління й суду великих землевласників та створювали органи місцевого самоврядування" flag="1"/>
    <answer text="Право, що встановлювало залежність селянина від феодала й водночас власність (неповну) останнього на селянина-кріпака" flag="0"/>
  </question>
  <question level="1" simple="True" text="Які з українських міст отримали маґдебурзьке право в XIV ст.?">
    <answer text="Сянок, Львів, Кам'янець, Холм, Перемишль" flag="1"/>
    <answer text="Луцьк, Київ, Кременець, Житомир, Дрогобич" flag="0"/>
  </question>
</testing>
