<?xml version="1.0" encoding="UTF-8"?>
<testing name="Восточнославянские племена - предки украинского - накануне образования государства">
  <question level="1" simple="True" text="Когда было образовано Дулибский племенной союз?">
    <answer text="Во 2 в." flag="0"/>
    <answer text="В 7 в." flag="1"/>
    <answer text="В 9 в." flag="0"/>
  </question>
  <question level="1" simple="True" text="Названия которых восточнославянских племенных союзов, доживших до времен образования государства на территории Украины, сохранил летопись?">
    <answer text="Словене, кривичи, радимичи, дреговичи и вятичи" flag="0"/>
    <answer text="Поляне, древляне, волыняне, хорваты, уличи, тиверцы и северяне" flag="1"/>
  </question>
  <question level="1" simple="True" text="Какую территорию занимал племенной восточнославянский союз полян?">
    <answer text="Среднее Поднепровье «в лесах на горах над рекой Днепром»" flag="1"/>
    <answer text="Между реками Случью и Днепром, Припятью и Тетерев" flag="0"/>
  </question>
  <question level="1" simple="True" text="Государство-сосед была главным торговым партнером восточнославянских союзов племен в 7-8 вв.?">
    <answer text="Хазарский каганат" flag="0"/>
    <answer text="Византийская империя" flag="1"/>
    <answer text="Польское княжество" flag="0"/>
  </question>
  <question level="1" simple="True" text="Из государств-соседей восточных славян господствовала в причерноморских степях до конца 10 в., Стремясь распространить на эти территории свою власть?">
    <answer text="Хазарский каганат" flag="1"/>
    <answer text="Аварский каганат" flag="0"/>
  </question>
  <question level="1" simple="True" text="Как называли воинов с севера - предков современных датчан, шведов, норвежцев, что нанимались к влиятельных властителей?">
    <answer text="Чудь, меря" flag="0"/>
    <answer text="Норманны, варяги" flag="1"/>
  </question>
  <question level="1" simple="True" text="Где был расположен племенной центр дулибского союза?">
    <answer text="В Зимненском городище, недалеко от Владимира на Волыни" flag="1"/>
    <answer text="В Киевском городище" flag="0"/>
  </question>
  <question level="1" simple="True" text="Какое из восточнославянских племенных объединений на территории Украины не входило в Дулибского племенного союза?">
    <answer text="Древляне" flag="0"/>
    <answer text="Северяне" flag="1"/>
    <answer text="Уличи" flag="0"/>
  </question>
  <question level="1" simple="True" text="Где, по мнению археологов, было расположено городище Кия?">
    <answer text="В северо-западной части Старокиевской горы" flag="1"/>
    <answer text="На Печерске" flag="0"/>
  </question>
  <question level="1" simple="True" text="Какая находка из археологических раскопок городища Кия свидетельствует о духовной жизни восточных славян?">
    <answer text="Збручский идол" flag="0"/>
    <answer text="Остатки древнего капища" flag="1"/>
  </question>
  <question level="1" simple="True" text="Как называют религиозные верования и обряды восточных славян, суть которых заключалась в обожествлении сил природы?">
    <answer text="Язычество" flag="1"/>
    <answer text="Христианство" flag="0"/>
  </question>
  <question level="1" simple="True" text="Как называется историческое произведение, в котором главные события записывались в хронологическом порядке по годам?">
    <answer text="Летопись" flag="1"/>
    <answer text="Поучения" flag="0"/>
    <answer text="Изборник" flag="0"/>
  </question>
</testing>
